brokjson/__init__.py
brokjson/__main__.py
brokJSON-1.0.0.dist-info/METADATA
brokJSON-1.0.0.dist-info/WHEEL
brokJSON-1.0.0.dist-info/top_level.txt
brokJSON-1.0.0.dist-info/RECORD
