Metadata-Version: 2.1
Name: brokJSON
Version: 1.0.0
Summary: Convert GeoJSON to BrokJSON and vice versa
Home-page: https://www.brokjson.dev
Author: Simon Huwiler
Author-email: webmaster@simonhuwiler.ch
License: MIT
Platform: UNKNOWN
Classifier: License :: OSI Approved :: MIT License
Classifier: Programming Language :: Python :: 3
Classifier: Programming Language :: Python :: 3.7
